dh_utils/UNI_BETA_LOWER.json
dh_utils/UNI_BETA_UPPER.json
dh_utils/__init__.py
dh_utils/tei.py
dh_utils/unicode.py
dh_utils/tei/__init__.py
dh_utils/tei/ca_template.xml
dh_utils/tei/crit_app.py
dh_utils/tei/markdown.py
dh_utils/tei/refsdecl_generator.py
dh_utils/tei/tag_script.py
dh_utils-0.1.23.dist-info/LICENSE
dh_utils-0.1.23.dist-info/METADATA
dh_utils-0.1.23.dist-info/WHEEL
dh_utils-0.1.23.dist-info/top_level.txt
dh_utils-0.1.23.dist-info/RECORD
