Metadata-Version: 2.1
Name: dh-utils
Version: 0.1.23
Summary: Python package containing various utilities relevant in the field of digital humanities.
Home-page: https://github.com/andredelft/dh-utils
Author: André van Delft
Author-email: andrevandelft@outlook.com
License: UNKNOWN
Keywords: digital humanities utilities unicode tei
Platform: UNKNOWN
Classifier: Development Status :: 4 - Beta
Classifier: Programming Language :: Python :: 3
Requires-Python: >=3.6
Requires-Dist: regex
Requires-Dist: lxml
Requires-Dist: anytree
Requires-Dist: markdown
Requires-Dist: namedentities
Provides-Extra: betacode
Requires-Dist: cltk ; extra == 'betacode'
